htmladapt/__init__.py
htmladapt/__main__.py
htmladapt/__version__.py
htmladapt/config.py
htmladapt/id_generation.py
htmladapt/matcher.py
htmladapt/parser.py
htmladapt/tool.py
htmladapt-1.0.12.dist-info/METADATA
htmladapt-1.0.12.dist-info/WHEEL
htmladapt-1.0.12.dist-info/entry_points.txt
htmladapt-1.0.12.dist-info/licenses/LICENSE
htmladapt-1.0.12.dist-info/RECORD
