Metadata-Version: 2.4
Name: htmladapt
Version: 1.0.12
Summary: Intelligent HTML content extraction and merge tool for bidirectional document transformation
Project-URL: Documentation, https://github.com/twardoch/htmladapt#readme
Project-URL: Issues, https://github.com/twardoch/htmladapt/issues
Project-URL: Source, https://github.com/twardoch/htmladapt
Author-email: Adam Twardoch <adam+github@twardoch.com>
License: MIT
License-File: LICENSE
Keywords: content-extraction,diff,html,merge,parsing,reconciliation,translation
Classifier: Development Status :: 4 - Beta
Classifier: Intended Audience :: Developers
Classifier: License :: OSI Approved :: MIT License
Classifier: Operating System :: OS Independent
Classifier: Programming Language :: Python
Classifier: Programming Language :: Python :: 3.10
Classifier: Programming Language :: Python :: 3.11
Classifier: Programming Language :: Python :: 3.12
Classifier: Programming Language :: Python :: Implementation :: CPython
Classifier: Programming Language :: Python :: Implementation :: PyPy
Requires-Python: >=3.10
Requires-Dist: beautifulsoup4>=4.12.0
Requires-Dist: fire>=0.4.0
Requires-Dist: html5lib>=1.1
Requires-Dist: lxml>=5.0.0
Requires-Dist: python-levenshtein>=0.20.0
Requires-Dist: rapidfuzz>=3.0.0
Requires-Dist: rich>=13.0.0
Requires-Dist: xxhash>=3.0.0
Requires-Dist: zss>=1.2.0
Provides-Extra: all
Requires-Dist: httpx>=0.25.0; extra == 'all'
Requires-Dist: openai>=1.0.0; extra == 'all'
Requires-Dist: tenacity>=8.2.0; extra == 'all'
Provides-Extra: dev
Requires-Dist: absolufy-imports>=0.3.1; extra == 'dev'
Requires-Dist: isort>=6.0.1; extra == 'dev'
Requires-Dist: mypy>=1.15.0; extra == 'dev'
Requires-Dist: pre-commit>=4.1.0; extra == 'dev'
Requires-Dist: pyupgrade>=3.19.1; extra == 'dev'
Requires-Dist: ruff>=0.9.7; extra == 'dev'
Provides-Extra: docs
Requires-Dist: myst-parser>=3.0.0; extra == 'docs'
Requires-Dist: sphinx-autodoc-typehints>=2.0.0; extra == 'docs'
Requires-Dist: sphinx-rtd-theme>=2.0.0; extra == 'docs'
Requires-Dist: sphinx>=7.2.6; extra == 'docs'
Provides-Extra: llm
Requires-Dist: httpx>=0.25.0; extra == 'llm'
Requires-Dist: openai>=1.0.0; extra == 'llm'
Requires-Dist: tenacity>=8.2.0; extra == 'llm'
Provides-Extra: test
Requires-Dist: coverage[toml]>=7.6.12; extra == 'test'
Requires-Dist: pytest-asyncio>=0.25.3; extra == 'test'
Requires-Dist: pytest-benchmark[histogram]>=5.1.0; extra == 'test'
Requires-Dist: pytest-cov>=6.0.0; extra == 'test'
Requires-Dist: pytest-xdist>=3.6.1; extra == 'test'
Requires-Dist: pytest>=8.3.4; extra == 'test'
